featurestorebundle/_config/.gitignore
featurestorebundle/_config/config.yaml
featurestorebundle/_config/config_test.yaml
featurestorebundle/checkpoint/CheckpointDirHandler.py
featurestorebundle/checkpoint/CheckpointGuard.py
featurestorebundle/databricks/DatabricksCurrentBranchResolver.py
featurestorebundle/databricks/DatabricksFeatureStoreClientFactory.py
featurestorebundle/databricks/feature/deleter/DatabricksFeatureStoreDeleter.py
featurestorebundle/databricks/feature/reader/DatabricksFeatureStoreReader.py
featurestorebundle/databricks/feature/writer/DatabricksFeatureStoreCreator.py
featurestorebundle/databricks/feature/writer/DatabricksFeatureStoreDataHandler.py
featurestorebundle/databricks/feature/writer/DatabricksFeatureStoreExistenceChecker.py
featurestorebundle/databricks/feature/writer/DatabricksFeatureStoreMergeConfig.py
featurestorebundle/databricks/feature/writer/DatabricksFeatureStorePreparer.py
featurestorebundle/databricks/feature/writer/DatabricksFeatureStoreWriter.py
featurestorebundle/db/TableNames.py
featurestorebundle/delta/DataFrameSchemaMerger.py
featurestorebundle/delta/EmptyDataFrameCreator.py
featurestorebundle/delta/feature/deleter/DeleteColumnsQueryBuilder.py
featurestorebundle/delta/feature/deleter/DeltaPathFeaturesDeleter.py
featurestorebundle/delta/feature/deleter/DeltaTableFeaturesDeleter.py
featurestorebundle/delta/feature/FeaturesJoiner.py
featurestorebundle/delta/feature/FeaturesPreparer.py
featurestorebundle/delta/feature/FeaturesPreparerTest.py
featurestorebundle/delta/feature/filter/FeaturesFilteringManager.py
featurestorebundle/delta/feature/filter/FeaturesFilteringManagerLatestTest.py
featurestorebundle/delta/feature/filter/FeaturesFilteringManagerTargetsTest.py
featurestorebundle/delta/feature/filter/IncompleteRowsHandler.py
featurestorebundle/delta/feature/filter/LatestFeaturesFilterer.py
featurestorebundle/delta/feature/filter/TargetFeaturesFilterer.py
featurestorebundle/delta/feature/NullHandler.py
feature_store_bundle-2.11.3.dist-info/entry_points.txt
feature_store_bundle-2.11.3.dist-info/LICENSE
feature_store_bundle-2.11.3.dist-info/METADATA
feature_store_bundle-2.11.3.dist-info/WHEEL
feature_store_bundle-2.11.3.dist-info/RECORD
