Metadata-Version: 2.1
Name: feature-store-bundle
Version: 2.11.3
Summary: Feature Store for the Daipe AI Platform
Home-page: https://github.com/daipe-ai/feature-store-bundle
License: Proprietary
Author: Datasentics
Author-email: jiri.koutny@datasentics.com
Requires-Python: >=3.8,<4.0
Classifier: License :: Other/Proprietary License
Classifier: Operating System :: OS Independent
Classifier: Programming Language :: Python :: 3
Classifier: Programming Language :: Python :: 3.8
Classifier: Programming Language :: Python :: 3.9
Classifier: Programming Language :: Python :: 3.10
Classifier: Programming Language :: Python :: 3.11
Classifier: Programming Language :: Python :: 3.12
Requires-Dist: daipe-core (>=1.4.2,<2.0.0)
Requires-Dist: databricks-bundle (>=1.4.12,<2.0.0)
Requires-Dist: pyfony-bundles (>=0.4.4,<0.5.0)
Project-URL: Repository, https://github.com/daipe-ai/feature-store-bundle
